{
    "meta": {
        "success": true,
        "message": "OK",
        "errorCode": -1
    },
    "data": {
        "deviceId": "3007",
        "sysModuleId": "DEVICE",
        "deviceName": "THINKPAD_SERVER1",
        "deviceEntryMode": -1,
        "deviceSerialNo": "IbOEHlOZQz",
        "config": "{\"deviceId\":3007,\"deviceName\":\"DVR SERVER 1\",\"nvrType\":\"MEDIA_GUARD\",\"dvrIp\":\"192.168.0.177\",\"dvrPort\":\"8080\",\"account\":\"admin\",\"password\":\"admin888\",\"siteId\":\"0\",\"maincomId\":\"6000014\"}",
        "mainComId": "6000014",
        "operatedUser": "SYSTEM",
        "updateDateTime": "2024-03-15T00:57:12.2815404+08:00",
        "status": 1,
        "siteId": "S2000",
        "isReverseHex": true
    }
}